ndf/__init__.py
ndf/parser.py
notedf-0.2.0.dist-info/licenses/LICENSE
notedf-0.2.0.dist-info/METADATA
notedf-0.2.0.dist-info/WHEEL
notedf-0.2.0.dist-info/top_level.txt
notedf-0.2.0.dist-info/RECORD
