Metadata-Version: 2.4
Name: notedf
Version: 0.2.0
Summary: Note Data Format - Simple, compact, model-optimized data format
Home-page: https://github.com/Dysporium/note-data-format
Author: Paul Mothapo
Author-email: Paul Mothapo <paulmothapo.business@gmail.com>
License: MIT
Project-URL: Homepage, https://github.com/Dysporium/note-data-format
Project-URL: Documentation, https://github.com/Dysporium/note-data-format#readme
Project-URL: Repository, https://github.com/Dysporium/note-data-format
Project-URL: Issues, https://github.com/Dysporium/note-data-format/issues
Keywords: data,format,serialization,parser,ai,ml
Classifier: Development Status :: 3 - Alpha
Classifier: Intended Audience :: Developers
Classifier: License :: OSI Approved :: MIT License
Classifier: Programming Language :: Python :: 3
Requires-Python: >=3.7
License-File: LICENSE
Dynamic: author
Dynamic: home-page
Dynamic: license-file
Dynamic: requires-python
